{"bycreator":"Johnson, Arnold A.","date_indexed":"2022-03-15T08:51:37Z","date_modified":"2022-03-15T08:51:37Z","dc":["510.mathematics"],"FulltextExist":true,"fulltext":"66\nJohnson,  Integral representations of hermitian forms over local fields\nnecessarily true.  If L is a p^O - modular plane,  then { q { x^ x ) \\x^ L } = uL r^ F and we\n( ^m i\\ ^^ ^ I where л^£ ) = uL and^isOif £L is isotropic and oc = —n^'^Qo\nif EL is anisotropic.  If L is a j9^D - modular lattice,  we can write L = Lq± H { i ) ± - • • ±H ( i ) where Lq is a modular line or plane and uLq = nL,  Finally,  if L and К are p * D - modular lattices,  then L is isometric to К if and only if nL = nK,  dim L : === dim if and d ( EL ) = d ( EK ), \nA natural question that arises is : \" Given a space F,  what kind of modular lattices will V support?  \".  If dim V is odd,  Lq in the above splitting is a modular line.  Therefore,  V will support a j9^D - modular lattice L if and only if i is even and then nL = /?  * D.  The interesting case is when dim V is even and here it is clear that we need only consider planes. \nNotice that for any ideal St,  we have p - ^SH^ Ш Т ( Ж ) ^ AD,  since Г ( 91 ) ф - ' is the largest ideal with trace in Г ( 21 ).  We will call a pair of ideals ( 21,  33 ) an allowable pair if 21 ^ S3 ^ 21® and an exceptional pair if 2Ï ^ 93 = 21®. \nProposition 7.  1.  Let V be a binary space and ( j^^D,  л'^Ю ) an allowable pair of ideals.  If ( j9 * D,  ji^^D ) is not an exceptional pair ( i.  e.  p^£ ) ^л^£ ) ^j9 * ~^® ),  then V supports a p^£ ) - modular lattice of norm л^£ ).  If ( p * D,  л'^О ) is an exceptional pair,  V must be a bolic plane to support such a lattice. \nProof,  Suppose first that p'£ ) ^л'^О ^ /?  ^ \" ^Ф.  Consider\nл ; * \" p'\nJ9 * ^ ОС\nThen EL is a binary space and by setting a = 0 or л'^~^QQ we obtain EL ^ V.  We note IhoX ос^л' - '^Qq^ ) : = л^ - '^ - ^Ъ^ ^л'^^ ) since я^О^у - ^Ф.  Thus nL = tt^^D. \nSuppose л ; * ^0 = р^Ъ,  Then setting a = 0,  we see that hyperbolic planes will support a desired lattice.  Conversely,  suppose V supports such a lattice with\noc = —л' - ''QQ^л''^,  Then л' - '^ - ^Ъ^ ^л'^^^р' - ^Ъ ^л \" ^^. \nIn the proof of the last proposition,  we saw that ос^л^£ ).  However,  we can actually say more,  i,  e,  oc^ T ( p^D ).  И л'^О = T ( p^D ) this is clear,  so suppose л'^Ю : =^ T ( p'D ).  Then since p'^S ) ^ T ( p'D ) ^p^'^'S ),  we have that jt^D ^^ \" '^ ( ^0 ) ^i?  ^~'®.  Thus oc d л' - '^ - ^^^ = л - '' ( р' - ^% ) ( p'^JS ) ) ^ T ( p'D ). \n^i \\ ^ we will mean L is\n/?  ^D - modular,  nL = л * ^£ ) and oc is either 0 or —tl^'^Qq depending on the situation at hand.  From this matrix,  we can read off immediately the pertinent information cerning the lattice L ; i.  e.  EL is isotropic or anisotropic,  ^L = /?  * D and nL = я * \" 0.  For\n^i \\ when we really mean a\nlattice L having this matrix.  This abuse of notation will also simplify the task of specifying\n^i + i ) of the lattice I ^^ ). \nFor any lattice L,  we define the dual lattice of L,  L \" ^ = { x^EL\\q { x,  L ) ^ D }.  We have ( L ± Z ) * = L * ± ÜC * ( L * ) * = L and if L is êL - modular,  L * is ( êL ) - ^ - modular.  These statements all follow immediately from the definition.  One other simple and important result is if L g Z are on the same space,  then Z * g L *. \n","fulltext_not_analysed":"66\nJohnson,  Integral representations of hermitian forms over local fields\nnecessarily true.  If L is a p^O - modular plane,  then { q { x^ x ) \\x^ L } = uL r^ F and we\n( ^m i\\ ^^ ^ I where л^£ ) = uL and^isOif £L is isotropic and oc = —n^'^Qo\nif EL is anisotropic.  If L is a j9^D - modular lattice,  we can write L = Lq± H { i ) ± - • • ±H ( i ) where Lq is a modular line or plane and uLq = nL,  Finally,  if L and К are p * D - modular lattices,  then L is isometric to К if and only if nL = nK,  dim L : === dim if and d ( EL ) = d ( EK ), \nA natural question that arises is : \" Given a space F,  what kind of modular lattices will V support?  \".  If dim V is odd,  Lq in the above splitting is a modular line.  Therefore,  V will support a j9^D - modular lattice L if and only if i is even and then nL = /?  * D.  The interesting case is when dim V is even and here it is clear that we need only consider planes. \nNotice that for any ideal St,  we have p - ^SH^ Ш Т ( Ж ) ^ AD,  since Г ( 91 ) ф - ' is the largest ideal with trace in Г ( 21 ).  We will call a pair of ideals ( 21,  33 ) an allowable pair if 21 ^ S3 ^ 21® and an exceptional pair if 2Ï ^ 93 = 21®. \nProposition 7.  1.  Let V be a binary space and ( j^^D,  л'^Ю ) an allowable pair of ideals.  If ( j9 * D,  ji^^D ) is not an exceptional pair ( i.  e.  p^£ ) ^л^£ ) ^j9 * ~^® ),  then V supports a p^£ ) - modular lattice of norm л^£ ).  If ( p * D,  л'^О ) is an exceptional pair,  V must be a bolic plane to support such a lattice. \nProof,  Suppose first that p'£ ) ^л'^О ^ /?  ^ \" ^Ф.  Consider\nл ; * \" p'\nJ9 * ^ ОС\nThen EL is a binary space and by setting a = 0 or л'^~^QQ we obtain EL ^ V.  We note IhoX ос^л' - '^Qq^ ) : = л^ - '^ - ^Ъ^ ^л'^^ ) since я^О^у - ^Ф.  Thus nL = tt^^D. \nSuppose л ; * ^0 = р^Ъ,  Then setting a = 0,  we see that hyperbolic planes will support a desired lattice.  Conversely,  suppose V supports such a lattice with\noc = —л' - ''QQ^л''^,  Then л' - '^ - ^Ъ^ ^л'^^^р' - ^Ъ ^л \" ^^. \nIn the proof of the last proposition,  we saw that ос^л^£ ).  However,  we can actually say more,  i,  e,  oc^ T ( p^D ).  И л'^О = T ( p^D ) this is clear,  so suppose л'^Ю : =^ T ( p'D ).  Then since p'^S ) ^ T ( p'D ) ^p^'^'S ),  we have that jt^D ^^ \" '^ ( ^0 ) ^i?  ^~'®.  Thus oc d л' - '^ - ^^^ = л - '' ( р' - ^% ) ( p'^JS ) ) ^ T ( p'D ). \n^i \\ ^ we will mean L is\n/?  ^D - modular,  nL = л * ^£ ) and oc is either 0 or —tl^'^Qq depending on the situation at hand.  From this matrix,  we can read off immediately the pertinent information cerning the lattice L ; i.  e.  EL is isotropic or anisotropic,  ^L = /?  * D and nL = я * \" 0.  For\n^i \\ when we really mean a\nlattice L having this matrix.  This abuse of notation will also simplify the task of specifying\n^i + i ) of the lattice I ^^ ). \nFor any lattice L,  we define the dual lattice of L,  L \" ^ = { x^EL\\q { x,  L ) ^ D }.  We have ( L ± Z ) * = L * ± ÜC * ( L * ) * = L and if L is êL - modular,  L * is ( êL ) - ^ - modular.  These statements all follow immediately from the definition.  One other simple and important result is if L g Z are on the same space,  then Z * g L *. \n","id":"indexer:243919689_0229:00000070","iscontribution":true,"label":"Integral representations of hermitian forms over local fields.","level":3,"log":"log10","log_id":"243919689_0229|log10","order":70,"orderlabel":"66","filename":"00000070.tif","format":"tif","page":"00000070","page_key":"indexer:243919689_0229:00000070","page_href":"http://www.digizeitschriften.de/master/PPN243919689_0229/00000070.tif","first_thumb_page_href":"","parent":{"parent_id":"243919689|log1","record_id":"243919689","record_identifier":"PPN243919689","log":"log1","title":{"title":"Journal für die reine und angewandte Mathematik","title_original":"Journal für die reine und angewandte Mathematik","sorttitle":"Journal für die reine und angewandte Mathematik"},"type":"periodical","issn":"00754102","dc":["510.mathematics"],"publish_infos":{"place_publish":["Berlin"],"place_info":[{"place_term":[{"type":"text","value":"Berlin"}]}],"publisher":["de Gruyter"],"year_publish_string":"1826","year_publish":1826,"year_publish_start":1826},"rights_access_condition_infos":[{"type":"dz","access_condition":"free"},{"type":"dz","access_condition":"Mathematics"}],"subject_infos":[{"authority":"gdz","topic":[{"Value":"jourfudi"}]}],"purl":"http://resolver.sub.uni-goettingen.de/purl?PID=243919689|log1"},"phys":"phys71","publish_infos":{"publisher":["de Gruyter"],"year_publish_string":"1968","year_publish":1968},"rights_access_condition_infos":[{"type":"dz","access_condition":"free"},{"type":"dz","access_condition":"Mathematics"}],"start_page_index":61,"end_page_index":84,"structrun":[{"parent_id":"243919689|log1","publish_infos":{"place_publish":["Berlin"],"place_info":[{"place_term":[{"type":"text","value":"Berlin"}]}],"publisher":["de Gruyter"],"year_publish_string":"1826","year_publish":1826,"year_publish_start":1826},"rights_access_condition_infos":[{"type":"dz","access_condition":"free"},{"type":"dz","access_condition":"Mathematics"}],"title":{"title":"Journal für die reine und angewandte Mathematik","title_original":"Journal für die reine und angewandte Mathematik","sorttitle":"Journal für die reine und angewandte Mathematik"},"type":"periodical","dc":["510.mathematics"],"issn":"00754102","purl":"http://resolver.sub.uni-goettingen.de/purl?PID=243919689|log1"},{"currentno":["229"],"currentnosort":2290,"parent_id":"243919689_0229|log1","publish_infos":{"publisher":["de Gruyter"],"year_publish_string":"1968","year_publish":1968},"rights_access_condition_infos":[{"type":"dz","access_condition":"free"},{"type":"dz","access_condition":"Mathematics"}],"title":{"title":"Journal für die reine und angewandte Mathematik","title_original":"Journal für die reine und angewandte Mathematik","sorttitle":"Journal für die reine und angewandte Mathematik"},"type":"volume","dc":["510.mathematics"]}],"title":{"title":"Integral representations of hermitian forms over local fields.","title_original":"Integral representations of hermitian forms over local fields.","sorttitle":"Integral representations of hermitian forms over local fields."},"type":"article","work":"243919689_0229","mimetype":"image/tif","Externalcontent":false,"Index":70}