{"bycreator":"Barner, Klaus","date_indexed":"2022-03-15T08:51:37Z","date_modified":"2022-03-15T08:51:37Z","dc":["510.mathematics"],"FulltextExist":true,"fulltext":"202 Da nun\nBarner,  Quaternäre Einheitsform in algebraischen Zahlkörpern\nÔ\n: 0 ( mod2 ), \nist ( 3.  18 ) dann und nur dann erfüllt,  wenn\n( 3.  19 ) ^ '^\nSetzen wir jetzt\n'K\\T\\ - ^\nWo ( mod 2 )\n( v = 0, . \n1 ). \nV = goYo + gl? !  H - - - - - - - - - \\ - Se - lYe - li\nso durchläuft ri ein vollständiges Restsystem modulo 2 in 0 ( K ),  wenn die g^,  g^, . . , ,  gß_^ unabhängig voneinander in 0 { T ) ein vollständiges Restsystem 9î mod 2 durchlaufen.  Sei 0.  B.  d.  A.  0,  1 Ç Ш.  Damit geht jedoch die Bedingung ( 3.  19 ) über in\n( 3.  20 ) g,  S^^^ ( ^ ] ^ +. . .  + g,  _,  S^^,  ( ^^\n0 ( mod 2 ), \n( ) ; : =0, . . . ,  6 -\n1 ). \nNun ist aber offenbar\nSk\\t ( ^^^j^ = 0 ( mod 2 ) für 2v ^ e, \nund unsere notwendige und hinreichende Bedingung ( 3.  20 ) reduziert sich unter tung von ( 3.  14 ) auf\n( 3.  21 ) g,  ^g,  ^^^'^ g^^^^ ^ 0 ( mod 2 ), \nwährend die übrigen ^^ € 9î mod 2 beliebig wählbar sind.  Die Anzahl der [ л,  für welche g^ mod 2 frei wählbar ist,  beträgt demnach\n( M - • ) =' -\ne + 1\nDaraus folgt : es gibt mod 2 genau\niVIL2\n[ l ]\nverschiedene Lösungen ту,  welche ( 3.  17 ) erfüllen.  Diese sind gegeben durch\n( 3.  22 ) n ^ giYx + g.  Yz + • • • + ge - iYe - i ^ gi^' - ^ + gz^' - ' + • • • + ge - 1 ( mod 2 ),  falls e = 2e * gerade,  und durch\n( 3.  23 ) ri ^ g,  y,  + g,  y,  + • • • + ^,  _2Г.  _2 ^ gi^' - ' + gz^''' + • • • + ^,  _2A ( mod2 ), \nfalls e = 2e * + 1 ungerade ist.  Wegen e *\nist damit Hilfssatz 3 bewiesen. \nHilfssatz 4.  Die Gesamtheit der nicht verschwindenden Summen G\\^\\ J^it e ^ q ^2e erhält man genau einmal,  wenn man im Falle e = 2e * in\n( 3.  24 ) G ( ^ ) = NV^' Z i\n\\^ I X mod 2\nYJQ in 0 ( K ) ein vollständiges Restsystem mod V * durchlaufen läßt,  und im Falle e = 2e * + 1,  wenn man in\nя ( ^ ), .  = д -.  ^, \n( 3.  25 )\nШ\nNV\ne + l\n^ e, \n/ Ai?  §a\n- ),  y = ^'^4, \nX mod 2 \\ 2 ö\nî / o Ш 0 ( ЛГ ) еш vollständiges Restsystem mod I^ * durchlaufen läßt. \n","fulltext_not_analysed":"202 Da nun\nBarner,  Quaternäre Einheitsform in algebraischen Zahlkörpern\nÔ\n: 0 ( mod2 ), \nist ( 3.  18 ) dann und nur dann erfüllt,  wenn\n( 3.  19 ) ^ '^\nSetzen wir jetzt\n'K\\T\\ - ^\nWo ( mod 2 )\n( v = 0, . \n1 ). \nV = goYo + gl? !  H - - - - - - - - - \\ - Se - lYe - li\nso durchläuft ri ein vollständiges Restsystem modulo 2 in 0 ( K ),  wenn die g^,  g^, . . , ,  gß_^ unabhängig voneinander in 0 { T ) ein vollständiges Restsystem 9î mod 2 durchlaufen.  Sei 0.  B.  d.  A.  0,  1 Ç Ш.  Damit geht jedoch die Bedingung ( 3.  19 ) über in\n( 3.  20 ) g,  S^^^ ( ^ ] ^ +. . .  + g,  _,  S^^,  ( ^^\n0 ( mod 2 ), \n( ) ; : =0, . . . ,  6 -\n1 ). \nNun ist aber offenbar\nSk\\t ( ^^^j^ = 0 ( mod 2 ) für 2v ^ e, \nund unsere notwendige und hinreichende Bedingung ( 3.  20 ) reduziert sich unter tung von ( 3.  14 ) auf\n( 3.  21 ) g,  ^g,  ^^^'^ g^^^^ ^ 0 ( mod 2 ), \nwährend die übrigen ^^ € 9î mod 2 beliebig wählbar sind.  Die Anzahl der [ л,  für welche g^ mod 2 frei wählbar ist,  beträgt demnach\n( M - • ) =' -\ne + 1\nDaraus folgt : es gibt mod 2 genau\niVIL2\n[ l ]\nverschiedene Lösungen ту,  welche ( 3.  17 ) erfüllen.  Diese sind gegeben durch\n( 3.  22 ) n ^ giYx + g.  Yz + • • • + ge - iYe - i ^ gi^' - ^ + gz^' - ' + • • • + ge - 1 ( mod 2 ),  falls e = 2e * gerade,  und durch\n( 3.  23 ) ri ^ g,  y,  + g,  y,  + • • • + ^,  _2Г.  _2 ^ gi^' - ' + gz^''' + • • • + ^,  _2A ( mod2 ), \nfalls e = 2e * + 1 ungerade ist.  Wegen e *\nist damit Hilfssatz 3 bewiesen. \nHilfssatz 4.  Die Gesamtheit der nicht verschwindenden Summen G\\^\\ J^it e ^ q ^2e erhält man genau einmal,  wenn man im Falle e = 2e * in\n( 3.  24 ) G ( ^ ) = NV^' Z i\n\\^ I X mod 2\nYJQ in 0 ( K ) ein vollständiges Restsystem mod V * durchlaufen läßt,  und im Falle e = 2e * + 1,  wenn man in\nя ( ^ ), .  = д -.  ^, \n( 3.  25 )\nШ\nNV\ne + l\n^ e, \n/ Ai?  §a\n- ),  y = ^'^4, \nX mod 2 \\ 2 ö\nî / o Ш 0 ( ЛГ ) еш vollständiges Restsystem mod I^ * durchlaufen läßt. \n","id":"indexer:243919689_0229:00000206","iscontribution":true,"label":"Über die quaternäre Einheitsform in total reellen algebraischen Zahlkörpern.","level":3,"log":"log21","log_id":"243919689_0229|log21","order":206,"orderlabel":"202","filename":"00000206.tif","format":"tif","page":"00000206","page_key":"indexer:243919689_0229:00000206","page_href":"http://www.digizeitschriften.de/master/PPN243919689_0229/00000206.tif","first_thumb_page_href":"","parent":{"parent_id":"243919689|log1","record_id":"243919689","record_identifier":"PPN243919689","log":"log1","title":{"title":"Journal für die reine und angewandte Mathematik","title_original":"Journal für die reine und angewandte Mathematik","sorttitle":"Journal für die reine und angewandte Mathematik"},"type":"periodical","issn":"00754102","dc":["510.mathematics"],"publish_infos":{"place_publish":["Berlin"],"place_info":[{"place_term":[{"type":"text","value":"Berlin"}]}],"publisher":["de Gruyter"],"year_publish_string":"1826","year_publish":1826,"year_publish_start":1826},"rights_access_condition_infos":[{"type":"dz","access_condition":"free"},{"type":"dz","access_condition":"Mathematics"}],"subject_infos":[{"authority":"gdz","topic":[{"Value":"jourfudi"}]}],"purl":"http://resolver.sub.uni-goettingen.de/purl?PID=243919689|log1"},"phys":"phys207","publish_infos":{"publisher":["de Gruyter"],"year_publish_string":"1968","year_publish":1968},"rights_access_condition_infos":[{"type":"dz","access_condition":"free"},{"type":"dz","access_condition":"Mathematics"}],"start_page_index":198,"end_page_index":212,"structrun":[{"parent_id":"243919689|log1","publish_infos":{"place_publish":["Berlin"],"place_info":[{"place_term":[{"type":"text","value":"Berlin"}]}],"publisher":["de Gruyter"],"year_publish_string":"1826","year_publish":1826,"year_publish_start":1826},"rights_access_condition_infos":[{"type":"dz","access_condition":"free"},{"type":"dz","access_condition":"Mathematics"}],"title":{"title":"Journal für die reine und angewandte Mathematik","title_original":"Journal für die reine und angewandte Mathematik","sorttitle":"Journal für die reine und angewandte Mathematik"},"type":"periodical","dc":["510.mathematics"],"issn":"00754102","purl":"http://resolver.sub.uni-goettingen.de/purl?PID=243919689|log1"},{"currentno":["229"],"currentnosort":2290,"parent_id":"243919689_0229|log1","publish_infos":{"publisher":["de Gruyter"],"year_publish_string":"1968","year_publish":1968},"rights_access_condition_infos":[{"type":"dz","access_condition":"free"},{"type":"dz","access_condition":"Mathematics"}],"title":{"title":"Journal für die reine und angewandte Mathematik","title_original":"Journal für die reine und angewandte Mathematik","sorttitle":"Journal für die reine und angewandte Mathematik"},"type":"volume","dc":["510.mathematics"]}],"title":{"title":"Über die quaternäre Einheitsform in total reellen algebraischen Zahlkörpern.","title_original":"Über die quaternäre Einheitsform in total reellen algebraischen Zahlkörpern.","sorttitle":"Über die quaternäre Einheitsform in total reellen algebraischen Zahlkörpern."},"type":"article","work":"243919689_0229","mimetype":"image/tif","Externalcontent":false,"Index":206}