{"bycreator":"Martinet, Jacques; Payan, Jean-Jacques","date_indexed":"2022-03-15T08:51:37Z","date_modified":"2022-03-15T08:51:37Z","dc":["510.mathematics"],"FulltextExist":true,"fulltext":"Martinet et Payan,  Sur les bases d^entiers des extensions galoisiennes de degré 6 33\nCas 4.  3 t л,  л : Ф db 1 mod 9.  On se ramène encore au cas où m^ = mg = 1 mod 3.  On peut prendre pour base\n1 + Ö + —\n1,  0,  —r—^.  ' ' 1 — /\nCas 9.  3 \\oc.  On se ramène au cas où 3 | m^,  3 t '^г - 0^ P^^^ prendre pour base\n1,  0,  1 - ^ - ' ' 1 — /\nBibliographie\n[ 1 ] N.  Bourlaki,  Algèbre commutative,  Chapitre 7,  Paris 1965. \n[ 2 ] A.  Fröhlich,  Ideals in an extension field as modules over the algebraic integers in a finite number field, \nMath.  Zeitschr.  74 ( 1960 ),  29—38.  [ 3 ] J.  Martinet et J.  J.  Payan,  Sur les extensions cubiques non galoisiennes des rationnels et leur clôture galoi -\nsienne,  Journal de Grelle — à paraître.  [ 4 ] J.  P.  Serre,  Corps locaux,  Paris 1962. \nEingegangen 1.  April 1966\nJournal für Mathematik.  Band 229\nб\n","fulltext_not_analysed":"Martinet et Payan,  Sur les bases d^entiers des extensions galoisiennes de degré 6 33\nCas 4.  3 t л,  л : Ф db 1 mod 9.  On se ramène encore au cas où m^ = mg = 1 mod 3.  On peut prendre pour base\n1 + Ö + —\n1,  0,  —r—^.  ' ' 1 — /\nCas 9.  3 \\oc.  On se ramène au cas où 3 | m^,  3 t '^г - 0^ P^^^ prendre pour base\n1,  0,  1 - ^ - ' ' 1 — /\nBibliographie\n[ 1 ] N.  Bourlaki,  Algèbre commutative,  Chapitre 7,  Paris 1965. \n[ 2 ] A.  Fröhlich,  Ideals in an extension field as modules over the algebraic integers in a finite number field, \nMath.  Zeitschr.  74 ( 1960 ),  29—38.  [ 3 ] J.  Martinet et J.  J.  Payan,  Sur les extensions cubiques non galoisiennes des rationnels et leur clôture galoi -\nsienne,  Journal de Grelle — à paraître.  [ 4 ] J.  P.  Serre,  Corps locaux,  Paris 1962. \nEingegangen 1.  April 1966\nJournal für Mathematik.  Band 229\nб\n","id":"indexer:243919689_0229:00000037","iscontribution":true,"label":"Sur les bases d'entiers des extensions galoisiennes et non abeliennes de degré 6 des rationnels.","level":3,"log":"log6","log_id":"243919689_0229|log6","order":37,"orderlabel":"33","filename":"00000037.tif","format":"tif","page":"00000037","page_key":"indexer:243919689_0229:00000037","page_href":"http://www.digizeitschriften.de/master/PPN243919689_0229/00000037.tif","first_thumb_page_href":"","parent":{"parent_id":"243919689|log1","record_id":"243919689","record_identifier":"PPN243919689","log":"log1","title":{"title":"Journal für die reine und angewandte Mathematik","title_original":"Journal für die reine und angewandte Mathematik","sorttitle":"Journal für die reine und angewandte Mathematik"},"type":"periodical","issn":"00754102","dc":["510.mathematics"],"publish_infos":{"place_publish":["Berlin"],"place_info":[{"place_term":[{"type":"text","value":"Berlin"}]}],"publisher":["de Gruyter"],"year_publish_string":"1826","year_publish":1826,"year_publish_start":1826},"rights_access_condition_infos":[{"type":"dz","access_condition":"free"},{"type":"dz","access_condition":"Mathematics"}],"subject_infos":[{"authority":"gdz","topic":[{"Value":"jourfudi"}]}],"purl":"http://resolver.sub.uni-goettingen.de/purl?PID=243919689|log1"},"phys":"phys38","publish_infos":{"publisher":["de Gruyter"],"year_publish_string":"1968","year_publish":1968},"rights_access_condition_infos":[{"type":"dz","access_condition":"free"},{"type":"dz","access_condition":"Mathematics"}],"start_page_index":33,"end_page_index":37,"structrun":[{"parent_id":"243919689|log1","publish_infos":{"place_publish":["Berlin"],"place_info":[{"place_term":[{"type":"text","value":"Berlin"}]}],"publisher":["de Gruyter"],"year_publish_string":"1826","year_publish":1826,"year_publish_start":1826},"rights_access_condition_infos":[{"type":"dz","access_condition":"free"},{"type":"dz","access_condition":"Mathematics"}],"title":{"title":"Journal für die reine und angewandte Mathematik","title_original":"Journal für die reine und angewandte Mathematik","sorttitle":"Journal für die reine und angewandte Mathematik"},"type":"periodical","dc":["510.mathematics"],"issn":"00754102","purl":"http://resolver.sub.uni-goettingen.de/purl?PID=243919689|log1"},{"currentno":["229"],"currentnosort":2290,"parent_id":"243919689_0229|log1","publish_infos":{"publisher":["de Gruyter"],"year_publish_string":"1968","year_publish":1968},"rights_access_condition_infos":[{"type":"dz","access_condition":"free"},{"type":"dz","access_condition":"Mathematics"}],"title":{"title":"Journal für die reine und angewandte Mathematik","title_original":"Journal für die reine und angewandte Mathematik","sorttitle":"Journal für die reine und angewandte Mathematik"},"type":"volume","dc":["510.mathematics"]}],"title":{"title":"Sur les bases d'entiers des extensions galoisiennes et non abeliennes de degré 6 des rationnels.","title_original":"Sur les bases d'entiers des extensions galoisiennes et non abeliennes de degré 6 des rationnels.","sorttitle":"Sur les bases d'entiers des extensions galoisiennes et non abeliennes de degré 6 des rationnels."},"type":"article","work":"243919689_0229","mimetype":"image/tif","Externalcontent":false,"Index":37}