{"bycreator":"Straub, Johannes","date_indexed":"2022-03-11T15:15:34Z","date_modified":"2022-03-11T15:15:34Z","dc":["900.history"],"FulltextExist":true,"fulltext":"William Seston : Dioclétien et la Tétrarchie\n497\nBoak 23 ) oder in Afrika { centuriaè ) auf örtliche Gepflogenheiten Rücksicht genommen wurde.  Freilich,  das System der Kollektiv - Verpflichtung und der alle fünf,  ab 312 alle fünfzehn Jahre neu festgesetzten Taxen beseitigte la liberté dans la répartition des charges et par conséquent la possibilité d * en discuter avec les agents de Vétat et de tenter une défense. \nKap.  2 { Uarmée,  les provinces et Vadministration centrale de Vempire ) geht von der Beobachtung aus,  daß Diokletians oberstes Ziel die Organisation einer schlagkräftigen Armee war,  der die Aufrechterhaltung der Ordnung im Innern und die Sicherung der Grenzen anvertraut werden konnte.  Über den Ausbau eines tief gestaffelten Verteidigungssystems an allen Fronten wurde schon gesprochen.  Die Heeresreform brachte die bekannte Vermehrung der Truppeneinheiten.  Für die Rekrutierung wurden den Grundbesitzern besondere Verpflichtungen auferlegt { prototypia — mit der capitatio aufs engste verkoppelt — rétablissement du rôle oà les contribuables de chaque capitulum étaient inscrits pour des sommes que le capitularius responsable fixait lui - même ; protostasia,  durch die en principe tout le monde est astreint^ ist die Verpflichtung zur Gestellung und Ausrüstung von Rekruten — hierzu ist eine eigene Untersuchung in der Appendice II vorgelegt ).  Den angestrebten Zweck erreichte Diokletian mit diesem Rekrutierungssystem nicht ; die wertvollsten Rekruten kamen ex cas tris,  bildeten die Freiwilligen aus den illyrischen,  keltischen,  germanischen Gebieten. \nDie seit Konstantin übliche Trennung zwischen limitanei und comita - tenses bahnt sich schon unter Diokletian an ; es gibt comités,  einen comitatus Augustorum,  eine mobile Reserve,  die unmittelbar unter dem Kommando der Herrscher steht.  — Die Truppen in den Grenzprovinzen werden jeweils einem dux,  einem praepositus limitis unterstellt,  ohne daß freilich die praesides schon aller militärischen Befehlsgewalt beraubt werden ; eine grundsätzliche Trennung zwischen Militär - und Zivilgewalt gibt es unter Diokletian noch nicht.  S.  betont sogar,  daß Diokletian a maintenu le principe de Vautorité des gouverneurs de province sur les troupes de leur ressort.  Es scheint aber doch,  daß all,  wo ein praepositus limitis oder dux eingesetzt war,  die Weisungsbefugnis des Statthalters auf bestimmte technische Bereiche beschränkt war,  etwa auf die von S.  zum Beweis herangezogene construction d * un fort in Numidien ( An.  Ép.  1942 / 3,  84 ).  — Die Senatoren waren unter den militärischen Chargen nicht mehr zu finden,  »weil sie selbst kein Interesse mehr am Militärdienst gehabt hätten«,  nicht weil sie grundsätzlich schon seit Gallie - nus ausgeschlossen worden seien ( die senatorischen Provinzstatthalter hatten ja die Befehlsgewalt über die in ihrem Bereich stationierten Truppen behalten ).  Durch die formelle Unterordnung der duces unter die praesides wurde zugleich die Macht der praef praet,  erheblich eingeschränkt. \nAuch in der réorganisation des provinces waren für Diokletian nach der Meinung von S.  ausschließlich militärische Gesichtspunkte maßgebend wesen : auf der einen Seite konnte durch die Verkleinerung der Provinzen und\n10»\n","fulltext_not_analysed":"William Seston : Dioclétien et la Tétrarchie\n497\nBoak 23 ) oder in Afrika { centuriaè ) auf örtliche Gepflogenheiten Rücksicht genommen wurde.  Freilich,  das System der Kollektiv - Verpflichtung und der alle fünf,  ab 312 alle fünfzehn Jahre neu festgesetzten Taxen beseitigte la liberté dans la répartition des charges et par conséquent la possibilité d * en discuter avec les agents de Vétat et de tenter une défense. \nKap.  2 { Uarmée,  les provinces et Vadministration centrale de Vempire ) geht von der Beobachtung aus,  daß Diokletians oberstes Ziel die Organisation einer schlagkräftigen Armee war,  der die Aufrechterhaltung der Ordnung im Innern und die Sicherung der Grenzen anvertraut werden konnte.  Über den Ausbau eines tief gestaffelten Verteidigungssystems an allen Fronten wurde schon gesprochen.  Die Heeresreform brachte die bekannte Vermehrung der Truppeneinheiten.  Für die Rekrutierung wurden den Grundbesitzern besondere Verpflichtungen auferlegt { prototypia — mit der capitatio aufs engste verkoppelt — rétablissement du rôle oà les contribuables de chaque capitulum étaient inscrits pour des sommes que le capitularius responsable fixait lui - même ; protostasia,  durch die en principe tout le monde est astreint^ ist die Verpflichtung zur Gestellung und Ausrüstung von Rekruten — hierzu ist eine eigene Untersuchung in der Appendice II vorgelegt ).  Den angestrebten Zweck erreichte Diokletian mit diesem Rekrutierungssystem nicht ; die wertvollsten Rekruten kamen ex cas tris,  bildeten die Freiwilligen aus den illyrischen,  keltischen,  germanischen Gebieten. \nDie seit Konstantin übliche Trennung zwischen limitanei und comita - tenses bahnt sich schon unter Diokletian an ; es gibt comités,  einen comitatus Augustorum,  eine mobile Reserve,  die unmittelbar unter dem Kommando der Herrscher steht.  — Die Truppen in den Grenzprovinzen werden jeweils einem dux,  einem praepositus limitis unterstellt,  ohne daß freilich die praesides schon aller militärischen Befehlsgewalt beraubt werden ; eine grundsätzliche Trennung zwischen Militär - und Zivilgewalt gibt es unter Diokletian noch nicht.  S.  betont sogar,  daß Diokletian a maintenu le principe de Vautorité des gouverneurs de province sur les troupes de leur ressort.  Es scheint aber doch,  daß all,  wo ein praepositus limitis oder dux eingesetzt war,  die Weisungsbefugnis des Statthalters auf bestimmte technische Bereiche beschränkt war,  etwa auf die von S.  zum Beweis herangezogene construction d * un fort in Numidien ( An.  Ép.  1942 / 3,  84 ).  — Die Senatoren waren unter den militärischen Chargen nicht mehr zu finden,  »weil sie selbst kein Interesse mehr am Militärdienst gehabt hätten«,  nicht weil sie grundsätzlich schon seit Gallie - nus ausgeschlossen worden seien ( die senatorischen Provinzstatthalter hatten ja die Befehlsgewalt über die in ihrem Bereich stationierten Truppen behalten ).  Durch die formelle Unterordnung der duces unter die praesides wurde zugleich die Macht der praef praet,  erheblich eingeschränkt. \nAuch in der réorganisation des provinces waren für Diokletian nach der Meinung von S.  ausschließlich militärische Gesichtspunkte maßgebend wesen : auf der einen Seite konnte durch die Verkleinerung der Provinzen und\n10»\n","id":"indexer:345204425_0001:00000500","iscontribution":true,"label":"Seston: Dioclétien et la Tétrarchie","level":4,"log":"log57","log_id":"345204425_0001|log57","order":500,"orderlabel":"497","filename":"00000500.tif","format":"tif","page":"00000500","page_key":"indexer:345204425_0001:00000500","page_href":"http://www.digizeitschriften.de/master/PPN345204425_0001/00000500.tif","first_thumb_page_href":"","page_height":4961,"page_width":3496,"parent":{"parent_id":"345204425|LOG_0000","record_id":"345204425","record_identifier":"PPN345204425","log":"LOG_0000","title":{"title":"Historia \u003cStuttgart\u003e","title_original":"Historia \u003cStuttgart\u003e","subtitle":"Zeitschrift für alte Geschichte","sorttitle":"Historia \u003cStuttgart\u003e"},"type":"periodical","issn":"00182311","zdb":"20752647","dc":["900.history"],"rights_access_condition_infos":[{"type":"copyright","copyright":"Steiner"},{"type":"dz","access_condition":"Gesamtabo"},{"type":"dz","access_condition":"Steiner","normalized_publisher":"Steiner"},{"type":"dz","access_condition":"History"}],"purl":"http://resolver.sub.uni-goettingen.de/purl?PID=345204425|LOG_0000","catalogue":"OPAC http://opac.sub.uni-goettingen.de/DB=1/PPN?PPN=345204425"},"phys":"phys501","publish_infos":{"place_publish":["Baden-Baden"],"place_info":[{"place_term":[{"type":"text","value":"Baden-Baden"}]}],"publisher":["Verl. für Kunst u. Wiss."],"year_publish_string":"1950","year_publish":1950},"rights_access_condition_infos":[{"type":"dz","access_condition":"Gesamtabo"},{"type":"dz","access_condition":"Steiner","normalized_publisher":"Steiner"},{"type":"dz","access_condition":"History"}],"start_page_index":490,"end_page_index":502,"structrun":[{"parent_id":"345204425|LOG_0000","rights_access_condition_infos":[{"type":"copyright","copyright":"Steiner"},{"type":"dz","access_condition":"Gesamtabo"},{"type":"dz","access_condition":"Steiner","normalized_publisher":"Steiner"},{"type":"dz","access_condition":"History"}],"title":{"title":"Historia \u003cStuttgart\u003e","title_original":"Historia \u003cStuttgart\u003e","subtitle":"Zeitschrift für alte Geschichte","sorttitle":"Historia \u003cStuttgart\u003e"},"type":"periodical","dc":["900.history"],"issn":"00182311","zdb":"20752647","purl":"http://resolver.sub.uni-goettingen.de/purl?PID=345204425|LOG_0000","catalogue":"OPAC http://opac.sub.uni-goettingen.de/DB=1/PPN?PPN=345204425"},{"currentno":["1"],"currentnosort":10,"parent_id":"345204425_0001|log1","publish_infos":{"place_publish":["Baden-Baden"],"place_info":[{"place_term":[{"type":"text","value":"Baden-Baden"}]}],"publisher":["Verl. für Kunst u. Wiss."],"year_publish_string":"1950","year_publish":1950},"rights_access_condition_infos":[{"type":"dz","access_condition":"Gesamtabo"},{"type":"dz","access_condition":"Steiner","normalized_publisher":"Steiner"},{"type":"dz","access_condition":"History"}],"title":{"title":"Historia","title_original":"Historia","sorttitle":"Historia"},"type":"volume","dc":["900.history"]},{"parent_id":"345204425_0001|log56","publish_infos":{"place_publish":["Baden-Baden"],"place_info":[{"place_term":[{"type":"text","value":"Baden-Baden"}]}],"publisher":["Verl. für Kunst u. Wiss."],"year_publish_string":"1950","year_publish":1950},"rights_access_condition_infos":[{"type":"dz","access_condition":"Gesamtabo"},{"type":"dz","access_condition":"Steiner","normalized_publisher":"Steiner"},{"type":"dz","access_condition":"History"}],"title":{"title":"Rezensionen","title_original":"Rezensionen","sorttitle":"Rezensionen"},"type":"part","dc":["900.history"]}],"title":{"title":"Seston: Dioclétien et la Tétrarchie","title_original":"Seston: Dioclétien et la Tétrarchie","sorttitle":"Seston: Dioclétien et la Tétrarchie"},"type":"review","work":"345204425_0001","mimetype":"image/tif","Externalcontent":false,"Index":500}