{"date_indexed":"2022-03-15T08:47:42Z","date_modified":"2022-03-15T08:47:42Z","dc":["340.law"],"FulltextExist":true,"fulltext":"— 40 —\nbeâ Stct^eâ ouf ®ultu§ unb Untemd^t auêgebel^nt tuirb.  einer glugfd^rift allerbingâ hjirb öertongt iSeftftöertüaltung in glei ( |för^ miger ©au®,  ©emetnbe» unb ^ßroöinjialberfaffung,  aber ba§ ift епЫ пзеЬег ber SBunf^ einer Strt bon дгипЬгефШфег Siegelung ber ©elbft^« Verwaltung,  ober её gehört in bie robilalen ^ßlüne einer Einteilung be§ ganjen Sleidieê in glei^ntä^ige SSertoaltungSbejirle.  ®ine ©egen® ftröntung gegen bie ertoä^nten jentraliftifd^en fÇorberungen ift im Slnfüng ber ^Bewegung ni^t öor^anben ; ber ©iftoriïer SSuttïe fte^t ollein,  wenn er bie Stngelegen^eiten ber inneren aSertoaltung,  alfo ba§,  ttiaê id^ bie materielle ©in^eit genannt ^abe,  freier SSereinbarung öorbe'^atten Wiffen toill. \n9lucE ) ber éntwurf ber 17 SRänner be§ öffentlid^en 3Sertrauen§\nfi ( | im ganjen an bie öon ber öffentlid^en 5Keinung gegebenen Sinien ; er fügt i^inju bie ©rteilung bon ©rfinbungê^jatenten für baS ©ebiet beê ganzen 9iei ( |eê,  ©efe^e über ^eimatâ® unb ©taatsbürger»' геф1 unb ba§ 3le ( ^t ber ÎReid^êgetoalt,  bie einzelnen ©taaten mit einer Stei^êfteuer gu belegen,  ßrft паф ber SSeröffentli^ung biefeè ®ntttiurfe§,  öon bem man wiffen ïonnte,  ob il ) n bie 3tational= berfommlung nid^t i^ren 39eratungen jugrunbe legen werbe,  ergebt fi^ eine eigentliche ) ) artilulariftif ( ^e ©egenftrömung ; fie ift am ftärf».  ften in ben SRittelftaaten,  wä^renb bie Äleinftaaten bie ganje 3eit 1^ { пЬигф ber ©in^^eit am wenigften ©^wierigïeiten in ben 358eg wer« fen ; fie tritt befonberê l^eröor in 8îat ) ern,  ba аиф offiziell,  unb in ^reu^en,  ba aber nur in ber öffentli^en SKeinung. \n®iefe ©egenftrömung ^at ein ftarï b^naftifd^^îonferôatioeê ©e - | ) гйде,  fie richtet ft^ befonber§ gegen bie Çaragra^j^en be§ ©ntwurfeè ber ©iebje^ner,  naä ) benen ber Äaifer bie Dffijiere be§ ftei^enben ®eere§ ernennt unb über feine SBerteilung öerfügt.  3 ) aê betrautet ber $arti» ïuIori8mu§ nid^t nur alê einen Eingriff in bie einjelftaatlidien 9led^te,  fonbern bireït alâ ©ïpro^iriierung.  éefonberâ bie ftreng ^jreu^if^e ©eftnnung ïann hierin nur eine ©elbftaufgabe felien unb warnt öor bet 3wfîimmung,  ba её einer Sluflöfung ^teu^enâ glei^ïomme,  wenn ber ©taat ni^t mei^t bie SSetfügung übet fein wid^tigfteâ SOta^t« mittel ^аЬе. \ngür $reu|en beïommen biefe ^eeteêfragen erft in bem Slugen» blid ein onbeteS ©efi^t,  wo её unöetrüdbar Mar ift,  bo§ ber Äönig öon ^teu^e'n als Kröger ber feinerfeitë feine mili»\ntärifфen Siedete aufgibt,  fonbern im ©egenteil feine Äommanbo«\n","fulltext_not_analysed":"— 40 —\nbeâ Stct^eâ ouf ®ultu§ unb Untemd^t auêgebel^nt tuirb.  einer glugfd^rift allerbingâ hjirb öertongt iSeftftöertüaltung in glei ( |för^ miger ©au®,  ©emetnbe» unb ^ßroöinjialberfaffung,  aber ba§ ift епЫ пзеЬег ber SBunf^ einer Strt bon дгипЬгефШфег Siegelung ber ©elbft^« Verwaltung,  ober её gehört in bie robilalen ^ßlüne einer Einteilung be§ ganjen Sleidieê in glei^ntä^ige SSertoaltungSbejirle.  ®ine ©egen® ftröntung gegen bie ertoä^nten jentraliftifd^en fÇorberungen ift im Slnfüng ber ^Bewegung ni^t öor^anben ; ber ©iftoriïer SSuttïe fte^t ollein,  wenn er bie Stngelegen^eiten ber inneren aSertoaltung,  alfo ba§,  ttiaê id^ bie materielle ©in^eit genannt ^abe,  freier SSereinbarung öorbe'^atten Wiffen toill. \n9lucE ) ber éntwurf ber 17 SRänner be§ öffentlid^en 3Sertrauen§\nfi ( | im ganjen an bie öon ber öffentlid^en 5Keinung gegebenen Sinien ; er fügt i^inju bie ©rteilung bon ©rfinbungê^jatenten für baS ©ebiet beê ganzen 9iei ( |eê,  ©efe^e über ^eimatâ® unb ©taatsbürger»' геф1 unb ba§ 3le ( ^t ber ÎReid^êgetoalt,  bie einzelnen ©taaten mit einer Stei^êfteuer gu belegen,  ßrft паф ber SSeröffentli^ung biefeè ®ntttiurfe§,  öon bem man wiffen ïonnte,  ob il ) n bie 3tational= berfommlung nid^t i^ren 39eratungen jugrunbe legen werbe,  ergebt fi^ eine eigentliche ) ) artilulariftif ( ^e ©egenftrömung ; fie ift am ftärf».  ften in ben SRittelftaaten,  wä^renb bie Äleinftaaten bie ganje 3eit 1^ { пЬигф ber ©in^^eit am wenigften ©^wierigïeiten in ben 358eg wer« fen ; fie tritt befonberê l^eröor in 8îat ) ern,  ba аиф offiziell,  unb in ^reu^en,  ba aber nur in ber öffentli^en SKeinung. \n®iefe ©egenftrömung ^at ein ftarï b^naftifd^^îonferôatioeê ©e - | ) гйде,  fie richtet ft^ befonber§ gegen bie Çaragra^j^en be§ ©ntwurfeè ber ©iebje^ner,  naä ) benen ber Äaifer bie Dffijiere be§ ftei^enben ®eere§ ernennt unb über feine SBerteilung öerfügt.  3 ) aê betrautet ber $arti» ïuIori8mu§ nid^t nur alê einen Eingriff in bie einjelftaatlidien 9led^te,  fonbern bireït alâ ©ïpro^iriierung.  éefonberâ bie ftreng ^jreu^if^e ©eftnnung ïann hierin nur eine ©elbftaufgabe felien unb warnt öor bet 3wfîimmung,  ba её einer Sluflöfung ^teu^enâ glei^ïomme,  wenn ber ©taat ni^t mei^t bie SSetfügung übet fein wid^tigfteâ SOta^t« mittel ^аЬе. \ngür $reu|en beïommen biefe ^eeteêfragen erft in bem Slugen» blid ein onbeteS ©efi^t,  wo её unöetrüdbar Mar ift,  bo§ ber Äönig öon ^teu^e'n als Kröger ber feinerfeitë feine mili»\ntärifфen Siedete aufgibt,  fonbern im ©egenteil feine Äommanbo«\n","id":"indexer:345574893_erg_003:00000050","iscontribution":false,"label":"Kapitel III. Die Reichsverfassung des ersten deutschen Parlaments","level":4,"log":"log11","log_id":"345574893_erg_003|log11","order":50,"orderlabel":"40","filename":"00000050.tif","format":"tif","page":"00000050","page_key":"indexer:345574893_erg_003:00000050","page_href":"http://www.digizeitschriften.de/master/PPN345574893_erg_003/00000050.tif","first_thumb_page_href":"","parent":{"parent_id":"345574893|log1","record_id":"345574893","record_identifier":"PPN345574893","log":"log1","title":{"title":"Archiv des öffentlichen Rechts","title_original":"Archiv des öffentlichen Rechts","sorttitle":"Archiv des öffentlichen Rechts"},"type":"periodical","issn":"00038911","zdb":"20757712","dc":["340.law"],"publish_infos":{"publisher":["Mohr Siebeck"]},"rights_access_condition_infos":[{"type":"dz","access_condition":"MohrSiebeck","normalized_publisher":"MohrSiebeck"},{"type":"dz","access_condition":"Gesamtabo"},{"type":"dz","access_condition":"Law"},{"type":"dz","access_condition":"free"},{"type":"copyright","copyright":"Mohr Siebeck"}],"subject_infos":[{"authority":"gdz","topic":[{"Value":"archdeoer"}]}],"purl":"http://resolver.sub.uni-goettingen.de/purl?PID=345574893|log1","catalogue":"OPAC http://opac.sub.uni-goettingen.de/DB=1/PPN?PPN=345574893"},"phys":"phys51","publish_infos":{"place_publish":["Tübingen"],"place_info":[{"place_term":[{"type":"text","value":"Tübingen"}]}],"publisher":["Mohr"],"year_publish_string":"1914","year_publish":1914},"rights_access_condition_infos":[{"type":"dz","access_condition":"MohrSiebeck","normalized_publisher":"MohrSiebeck"},{"type":"dz","access_condition":"free"},{"type":"dz","access_condition":"Law"}],"start_page_index":40,"end_page_index":80,"structrun":[{"parent_id":"345574893|log1","publish_infos":{"publisher":["Mohr Siebeck"]},"rights_access_condition_infos":[{"type":"dz","access_condition":"MohrSiebeck","normalized_publisher":"MohrSiebeck"},{"type":"dz","access_condition":"Gesamtabo"},{"type":"dz","access_condition":"Law"},{"type":"dz","access_condition":"free"},{"type":"copyright","copyright":"Mohr Siebeck"}],"title":{"title":"Archiv des öffentlichen Rechts","title_original":"Archiv des öffentlichen Rechts","sorttitle":"Archiv des öffentlichen Rechts"},"type":"periodical","dc":["340.law"],"issn":"00038911","zdb":"20757712","purl":"http://resolver.sub.uni-goettingen.de/purl?PID=345574893|log1","catalogue":"OPAC http://opac.sub.uni-goettingen.de/DB=1/PPN?PPN=345574893"},{"currentno":["Ergänzungsband 3"],"currentnosort":321,"parent_id":"345574893_erg_003|log1","publish_infos":{"place_publish":["Tübingen"],"place_info":[{"place_term":[{"type":"text","value":"Tübingen"}]}],"publisher":["Mohr"],"year_publish_string":"1914","year_publish":1914},"rights_access_condition_infos":[{"type":"dz","access_condition":"MohrSiebeck","normalized_publisher":"MohrSiebeck"},{"type":"dz","access_condition":"free"},{"type":"dz","access_condition":"Law"}],"title":{"title":"Archiv des öffentlichen Rechts / III. Beilageheft","title_original":"Archiv des öffentlichen Rechts / III. Beilageheft","sorttitle":"Archiv des öffentlichen Rechts / III. Beilageheft"},"type":"volume","dc":["340.law"]},{"parent_id":"345574893_erg_003|log4","publish_infos":{"place_publish":["Tübingen"],"place_info":[{"place_term":[{"type":"text","value":"Tübingen"}]}],"publisher":["Mohr"],"year_publish_string":"1914","year_publish":1914},"rights_access_condition_infos":[{"type":"dz","access_condition":"MohrSiebeck","normalized_publisher":"MohrSiebeck"},{"type":"dz","access_condition":"free"},{"type":"dz","access_condition":"Law"}],"title":{"title":"Geschichte der Reichsverfassung","title_original":"Geschichte der Reichsverfassung","sorttitle":"Geschichte der Reichsverfassung"},"type":"article","dc":["340.law"]}],"title":{"title":"Kapitel III. Die Reichsverfassung des ersten deutschen Parlaments","title_original":"Kapitel III. Die Reichsverfassung des ersten deutschen Parlaments","sorttitle":"Kapitel III. Die Reichsverfassung des ersten deutschen Parlaments"},"type":"chapter","work":"345574893_erg_003","mimetype":"image/tif","Externalcontent":false,"Index":50}