{"date_indexed":"2022-03-15T08:47:42Z","date_modified":"2022-03-15T08:47:42Z","dc":["340.law"],"FulltextExist":true,"fulltext":"— 110 —\nmen ).  ( Sbenfo ïônnen bie öter fübbeutj ( ^en ©taaten Samern,  Шйxt^ temberg,  ®oben ( 3 ),  Reffen ( 3 ) jcgli^e SSctfoffungäünbetung »er» l^inbcm.  Фтф baê ^tnjuîommen bet elfa^^ot^ringif^en Stimmen ift,  №ie ettoä^nt,  ^ietan nid\u003etê geänbett. \ndaneben ift in ben SBer^anblnngen mit Samern unb SBütttem» betg an gtoei ©teilen bet Sîetfafjung апф eine Slenbemng im ©inné bet fttoffeten ®in^eit etfolgt : ©eibe ©toaten gaben gemeinsam bie Stnregung,  bie Äompetenj beê 3leid ) eê auèjube^nen auf bie 58eftim» mungen übet bie ^teffe unb ba§ SSereinêloefen.  33eibe Staaten fatten |фоп eine übetauä fteie ©efefegebung übet biefe ©egenftünbe unb e§ ift anjune^men,  ba^ fie hofften,  Ьшф bie 9ïei ( ^êgefe|gebung einige toStDüd^fe äu befeitigen.  Xotföd^lid ) ^at fie ouf feinem anbeten ©ebiete fo lange Watten laffen,  wie gerabe auf biefem.  @tft im ga^te 1909 toutbe ein 9leid ) §tietein§gefefe etlaffen,  eine bet ^rüd^te be0 fog.  ©todreic^iêtageê.  : ^at gto^e ©tleii^tetungen getabe für bie ) 3oIitif^en 35eteine gebta^t,  beten SSitïfamïeit in einet gtoßen Slnjat )!  bon 83unbe§ftaaten bamit erft eigentlid ) gefid^ert würbe öot WilHürlid^en Eingriffen ber ^olijeibetiörben unb bet SSerWaltung.  Sßid^tiget nodt ) war,  bog auf SBo^ernê SSeronloffung bie SKotine jur 9lei^§fodf ) e gemocht würbe.  $ie SSerfaffung beê Sîorbbeutfd^en Sôunbeê lannte nut eine SSunbeêmotine untet ^Jteufeifd^em Ober» befell.  Sotjern weigerte fi«^ junäc^ft,  ju biefet Sölarine finonsielt beizutragen,  ba für feine binnenlänbifdf ) en SSerpitniffe ein SSebûrfniê nod^ einet ©eewel^r über^aitpt nid^t öorliege. .  50ian tonnte jo oudt»,  ouêge^enb toon ber botUegenben Setfaffung,  bie SUlorine atö eine : ^au| ) tfäd^Iid^ ïireugifd^e Slngelegeni^eit onfe^en,  für bie nur etwo nod^ bie anbeten Süflenfloaten ein ^wtereffe l^ötten.  ÄugenbM,  wo bie SKarine ofô Steid^êinftitution bem toifer unterftelft Wutbe,  Wor SSo^em burd^ ben ®unbeätot in enge Säejie^ung aud^ ju biefem ©tüde.  ber nationolen Slttflimg gefegt unb ïonnte fid^ felbftberftänbtid^ bem Seitwge nid^t me : ^r entjie^en. \nStofe biefet Äuäna^men erfd^ien im großen unb ganjen burd^ bic ®ebingungen,  bie SBa^em on feinen dintritt inê Sleid^ Inüpfte,  bo8 föberoliftifd^e ^rinji!  ) in ber 9leidf ) §t ) etfaffung bon neuem be= träd^tlid^ geftürlt ; ein Seit ber öffentlid^en SReinung,  ber gonje Sibe« raltêmuê,  wor borum mit biefen f onjeffionen butd^ouä nid^t fonberlid^ jufriebcn,  wenn et fie oud^ ) fd^ilieglid^ onnol^m.  éiâmord wußte ba§ fe^t wo^I unb ^atte ïïug genug fd^on wä^renb bet ®er^onbIungen\n","fulltext_not_analysed":"— 110 —\nmen ).  ( Sbenfo ïônnen bie öter fübbeutj ( ^en ©taaten Samern,  Шйxt^ temberg,  ®oben ( 3 ),  Reffen ( 3 ) jcgli^e SSctfoffungäünbetung »er» l^inbcm.  Фтф baê ^tnjuîommen bet elfa^^ot^ringif^en Stimmen ift,  №ie ettoä^nt,  ^ietan nid\u003etê geänbett. \ndaneben ift in ben SBer^anblnngen mit Samern unb SBütttem» betg an gtoei ©teilen bet Sîetfafjung апф eine Slenbemng im ©inné bet fttoffeten ®in^eit etfolgt : ©eibe ©toaten gaben gemeinsam bie Stnregung,  bie Äompetenj beê 3leid ) eê auèjube^nen auf bie 58eftim» mungen übet bie ^teffe unb ba§ SSereinêloefen.  33eibe Staaten fatten |фоп eine übetauä fteie ©efefegebung übet biefe ©egenftünbe unb e§ ift anjune^men,  ba^ fie hofften,  Ьшф bie 9ïei ( ^êgefe|gebung einige toStDüd^fe äu befeitigen.  Xotföd^lid ) ^at fie ouf feinem anbeten ©ebiete fo lange Watten laffen,  wie gerabe auf biefem.  @tft im ga^te 1909 toutbe ein 9leid ) §tietein§gefefe etlaffen,  eine bet ^rüd^te be0 fog.  ©todreic^iêtageê.  : ^at gto^e ©tleii^tetungen getabe für bie ) 3oIitif^en 35eteine gebta^t,  beten SSitïfamïeit in einet gtoßen Slnjat )!  bon 83unbe§ftaaten bamit erft eigentlid ) gefid^ert würbe öot WilHürlid^en Eingriffen ber ^olijeibetiörben unb bet SSerWaltung.  Sßid^tiget nodt ) war,  bog auf SBo^ernê SSeronloffung bie SKotine jur 9lei^§fodf ) e gemocht würbe.  $ie SSerfaffung beê Sîorbbeutfd^en Sôunbeê lannte nut eine SSunbeêmotine untet ^Jteufeifd^em Ober» befell.  Sotjern weigerte fi«^ junäc^ft,  ju biefet Sölarine finonsielt beizutragen,  ba für feine binnenlänbifdf ) en SSerpitniffe ein SSebûrfniê nod^ einet ©eewel^r über^aitpt nid^t öorliege. .  50ian tonnte jo oudt»,  ouêge^enb toon ber botUegenben Setfaffung,  bie SUlorine atö eine : ^au| ) tfäd^Iid^ ïireugifd^e Slngelegeni^eit onfe^en,  für bie nur etwo nod^ bie anbeten Süflenfloaten ein ^wtereffe l^ötten.  ÄugenbM,  wo bie SKarine ofô Steid^êinftitution bem toifer unterftelft Wutbe,  Wor SSo^em burd^ ben ®unbeätot in enge Säejie^ung aud^ ju biefem ©tüde.  ber nationolen Slttflimg gefegt unb ïonnte fid^ felbftberftänbtid^ bem Seitwge nid^t me : ^r entjie^en. \nStofe biefet Äuäna^men erfd^ien im großen unb ganjen burd^ bic ®ebingungen,  bie SBa^em on feinen dintritt inê Sleid^ Inüpfte,  bo8 föberoliftifd^e ^rinji!  ) in ber 9leidf ) §t ) etfaffung bon neuem be= träd^tlid^ geftürlt ; ein Seit ber öffentlid^en SReinung,  ber gonje Sibe« raltêmuê,  wor borum mit biefen f onjeffionen butd^ouä nid^t fonberlid^ jufriebcn,  wenn et fie oud^ ) fd^ilieglid^ onnol^m.  éiâmord wußte ba§ fe^t wo^I unb ^atte ïïug genug fd^on wä^renb bet ®er^onbIungen\n","id":"indexer:345574893_erg_003:00000120","iscontribution":false,"label":"Kapitel V. Die Reichsgründung 1870/71","level":4,"log":"log13","log_id":"345574893_erg_003|log13","order":120,"orderlabel":"110","filename":"00000120.tif","format":"tif","page":"00000120","page_key":"indexer:345574893_erg_003:00000120","page_href":"http://www.digizeitschriften.de/master/PPN345574893_erg_003/00000120.tif","first_thumb_page_href":"","parent":{"parent_id":"345574893|log1","record_id":"345574893","record_identifier":"PPN345574893","log":"log1","title":{"title":"Archiv des öffentlichen Rechts","title_original":"Archiv des öffentlichen Rechts","sorttitle":"Archiv des öffentlichen Rechts"},"type":"periodical","issn":"00038911","zdb":"20757712","dc":["340.law"],"publish_infos":{"publisher":["Mohr Siebeck"]},"rights_access_condition_infos":[{"type":"dz","access_condition":"MohrSiebeck","normalized_publisher":"MohrSiebeck"},{"type":"dz","access_condition":"Gesamtabo"},{"type":"dz","access_condition":"Law"},{"type":"dz","access_condition":"free"},{"type":"copyright","copyright":"Mohr Siebeck"}],"subject_infos":[{"authority":"gdz","topic":[{"Value":"archdeoer"}]}],"purl":"http://resolver.sub.uni-goettingen.de/purl?PID=345574893|log1","catalogue":"OPAC http://opac.sub.uni-goettingen.de/DB=1/PPN?PPN=345574893"},"phys":"phys121","publish_infos":{"place_publish":["Tübingen"],"place_info":[{"place_term":[{"type":"text","value":"Tübingen"}]}],"publisher":["Mohr"],"year_publish_string":"1914","year_publish":1914},"rights_access_condition_infos":[{"type":"dz","access_condition":"MohrSiebeck","normalized_publisher":"MohrSiebeck"},{"type":"dz","access_condition":"free"},{"type":"dz","access_condition":"Law"}],"start_page_index":115,"end_page_index":122,"structrun":[{"parent_id":"345574893|log1","publish_infos":{"publisher":["Mohr Siebeck"]},"rights_access_condition_infos":[{"type":"dz","access_condition":"MohrSiebeck","normalized_publisher":"MohrSiebeck"},{"type":"dz","access_condition":"Gesamtabo"},{"type":"dz","access_condition":"Law"},{"type":"dz","access_condition":"free"},{"type":"copyright","copyright":"Mohr Siebeck"}],"title":{"title":"Archiv des öffentlichen Rechts","title_original":"Archiv des öffentlichen Rechts","sorttitle":"Archiv des öffentlichen Rechts"},"type":"periodical","dc":["340.law"],"issn":"00038911","zdb":"20757712","purl":"http://resolver.sub.uni-goettingen.de/purl?PID=345574893|log1","catalogue":"OPAC http://opac.sub.uni-goettingen.de/DB=1/PPN?PPN=345574893"},{"currentno":["Ergänzungsband 3"],"currentnosort":321,"parent_id":"345574893_erg_003|log1","publish_infos":{"place_publish":["Tübingen"],"place_info":[{"place_term":[{"type":"text","value":"Tübingen"}]}],"publisher":["Mohr"],"year_publish_string":"1914","year_publish":1914},"rights_access_condition_infos":[{"type":"dz","access_condition":"MohrSiebeck","normalized_publisher":"MohrSiebeck"},{"type":"dz","access_condition":"free"},{"type":"dz","access_condition":"Law"}],"title":{"title":"Archiv des öffentlichen Rechts / III. Beilageheft","title_original":"Archiv des öffentlichen Rechts / III. Beilageheft","sorttitle":"Archiv des öffentlichen Rechts / III. Beilageheft"},"type":"volume","dc":["340.law"]},{"parent_id":"345574893_erg_003|log4","publish_infos":{"place_publish":["Tübingen"],"place_info":[{"place_term":[{"type":"text","value":"Tübingen"}]}],"publisher":["Mohr"],"year_publish_string":"1914","year_publish":1914},"rights_access_condition_infos":[{"type":"dz","access_condition":"MohrSiebeck","normalized_publisher":"MohrSiebeck"},{"type":"dz","access_condition":"free"},{"type":"dz","access_condition":"Law"}],"title":{"title":"Geschichte der Reichsverfassung","title_original":"Geschichte der Reichsverfassung","sorttitle":"Geschichte der Reichsverfassung"},"type":"article","dc":["340.law"]}],"title":{"title":"Kapitel V. Die Reichsgründung 1870/71","title_original":"Kapitel V. Die Reichsgründung 1870/71","sorttitle":"Kapitel V. Die Reichsgründung 1870/71"},"type":"chapter","work":"345574893_erg_003","mimetype":"image/tif","Externalcontent":false,"Index":120}